{
  "#changelog": {
    "current": {
      "number": "8",
      "spec": "Web MIDI API",
      "text": "Changelog",
      "url": "https://webaudio.github.io/web-midi-api/#changelog"
    },
    "snapshot": {
      "number": "8",
      "spec": "Web MIDI API",
      "text": "Changelog",
      "url": "https://www.w3.org/TR/webmidi/#changelog"
    }
  },
  "#changes-since-working-draft-17-march-2015": {
    "current": {
      "number": "8.1",
      "spec": "Web MIDI API",
      "text": "Changes since Working Draft 17 March 2015",
      "url": "https://webaudio.github.io/web-midi-api/#changes-since-working-draft-17-march-2015"
    },
    "snapshot": {
      "number": "8.1",
      "spec": "Web MIDI API",
      "text": "Changes since Working Draft 17 March 2015",
      "url": "https://www.w3.org/TR/webmidi/#changes-since-working-draft-17-march-2015"
    }
  },
  "#conformance": {
    "current": {
      "number": "2",
      "spec": "Web MIDI API",
      "text": "Conformance",
      "url": "https://webaudio.github.io/web-midi-api/#conformance"
    },
    "snapshot": {
      "number": "2",
      "spec": "Web MIDI API",
      "text": "Conformance",
      "url": "https://www.w3.org/TR/webmidi/#conformance"
    }
  },
  "#extensions-to-the-navigator-interface": {
    "current": {
      "number": "4.3",
      "spec": "Web MIDI API",
      "text": "Extensions to the Navigator interface",
      "url": "https://webaudio.github.io/web-midi-api/#extensions-to-the-navigator-interface"
    },
    "snapshot": {
      "number": "4.3",
      "spec": "Web MIDI API",
      "text": "Extensions to the Navigator interface",
      "url": "https://www.w3.org/TR/webmidi/#extensions-to-the-navigator-interface"
    }
  },
  "#introduction": {
    "current": {
      "number": "1",
      "spec": "Web MIDI API",
      "text": "Introduction",
      "url": "https://webaudio.github.io/web-midi-api/#introduction"
    },
    "snapshot": {
      "number": "1",
      "spec": "Web MIDI API",
      "text": "Introduction",
      "url": "https://www.w3.org/TR/webmidi/#introduction"
    }
  },
  "#midiaccess-interface": {
    "current": {
      "number": "5.3",
      "spec": "Web MIDI API",
      "text": "MIDIAccess Interface",
      "url": "https://webaudio.github.io/web-midi-api/#midiaccess-interface"
    },
    "snapshot": {
      "number": "5.3",
      "spec": "Web MIDI API",
      "text": "MIDIAccess Interface",
      "url": "https://www.w3.org/TR/webmidi/#midiaccess-interface"
    }
  },
  "#midiconnectionevent-interface": {
    "current": {
      "number": "5.6",
      "spec": "Web MIDI API",
      "text": "MIDIConnectionEvent Interface",
      "url": "https://webaudio.github.io/web-midi-api/#midiconnectionevent-interface"
    },
    "snapshot": {
      "number": "5.6",
      "spec": "Web MIDI API",
      "text": "MIDIConnectionEvent Interface",
      "url": "https://www.w3.org/TR/webmidi/#midiconnectionevent-interface"
    }
  },
  "#midiconnectioneventinit-dictionary": {
    "current": {
      "number": "5.6.1",
      "spec": "Web MIDI API",
      "text": "MIDIConnectionEventInit Dictionary",
      "url": "https://webaudio.github.io/web-midi-api/#midiconnectioneventinit-dictionary"
    },
    "snapshot": {
      "number": "5.6.1",
      "spec": "Web MIDI API",
      "text": "MIDIConnectionEventInit Dictionary",
      "url": "https://www.w3.org/TR/webmidi/#midiconnectioneventinit-dictionary"
    }
  },
  "#midiinput-interface": {
    "current": {
      "number": "5.4.1",
      "spec": "Web MIDI API",
      "text": "MIDIInput Interface",
      "url": "https://webaudio.github.io/web-midi-api/#midiinput-interface"
    },
    "snapshot": {
      "number": "5.4.1",
      "spec": "Web MIDI API",
      "text": "MIDIInput Interface",
      "url": "https://www.w3.org/TR/webmidi/#midiinput-interface"
    }
  },
  "#midiinputmap-interface": {
    "current": {
      "number": "5.1",
      "spec": "Web MIDI API",
      "text": "MIDIInputMap Interface",
      "url": "https://webaudio.github.io/web-midi-api/#midiinputmap-interface"
    },
    "snapshot": {
      "number": "5.1",
      "spec": "Web MIDI API",
      "text": "MIDIInputMap Interface",
      "url": "https://www.w3.org/TR/webmidi/#midiinputmap-interface"
    }
  },
  "#midimessageevent-interface": {
    "current": {
      "number": "5.5",
      "spec": "Web MIDI API",
      "text": "MIDIMessageEvent Interface",
      "url": "https://webaudio.github.io/web-midi-api/#midimessageevent-interface"
    },
    "snapshot": {
      "number": "5.5",
      "spec": "Web MIDI API",
      "text": "MIDIMessageEvent Interface",
      "url": "https://www.w3.org/TR/webmidi/#midimessageevent-interface"
    }
  },
  "#midimessageeventinit-dictionary": {
    "current": {
      "number": "5.5.1",
      "spec": "Web MIDI API",
      "text": "MIDIMessageEventInit Dictionary",
      "url": "https://webaudio.github.io/web-midi-api/#midimessageeventinit-dictionary"
    },
    "snapshot": {
      "number": "5.5.1",
      "spec": "Web MIDI API",
      "text": "MIDIMessageEventInit Dictionary",
      "url": "https://www.w3.org/TR/webmidi/#midimessageeventinit-dictionary"
    }
  },
  "#midioptions-dictionary": {
    "current": {
      "number": "4.3.1",
      "spec": "Web MIDI API",
      "text": "MIDIOptions Dictionary",
      "url": "https://webaudio.github.io/web-midi-api/#midioptions-dictionary"
    },
    "snapshot": {
      "number": "4.3.1",
      "spec": "Web MIDI API",
      "text": "MIDIOptions Dictionary",
      "url": "https://www.w3.org/TR/webmidi/#midioptions-dictionary"
    }
  },
  "#midioutput-interface": {
    "current": {
      "number": "5.4.2",
      "spec": "Web MIDI API",
      "text": "MIDIOutput Interface",
      "url": "https://webaudio.github.io/web-midi-api/#midioutput-interface"
    },
    "snapshot": {
      "number": "5.4.2",
      "spec": "Web MIDI API",
      "text": "MIDIOutput Interface",
      "url": "https://www.w3.org/TR/webmidi/#midioutput-interface"
    }
  },
  "#midioutputmap-interface": {
    "current": {
      "number": "5.2",
      "spec": "Web MIDI API",
      "text": "MIDIOutputMap Interface",
      "url": "https://webaudio.github.io/web-midi-api/#midioutputmap-interface"
    },
    "snapshot": {
      "number": "5.2",
      "spec": "Web MIDI API",
      "text": "MIDIOutputMap Interface",
      "url": "https://www.w3.org/TR/webmidi/#midioutputmap-interface"
    }
  },
  "#midiport-interface": {
    "current": {
      "number": "5.4",
      "spec": "Web MIDI API",
      "text": "MIDIPort Interface",
      "url": "https://webaudio.github.io/web-midi-api/#midiport-interface"
    },
    "snapshot": {
      "number": "5.4",
      "spec": "Web MIDI API",
      "text": "MIDIPort Interface",
      "url": "https://www.w3.org/TR/webmidi/#midiport-interface"
    }
  },
  "#midiportconnectionstate-enum": {
    "current": {
      "number": "5.4.5",
      "spec": "Web MIDI API",
      "text": "MIDIPortConnectionState Enum",
      "url": "https://webaudio.github.io/web-midi-api/#midiportconnectionstate-enum"
    },
    "snapshot": {
      "number": "5.4.5",
      "spec": "Web MIDI API",
      "text": "MIDIPortConnectionState Enum",
      "url": "https://www.w3.org/TR/webmidi/#midiportconnectionstate-enum"
    }
  },
  "#midiportdevicestate-enum": {
    "current": {
      "number": "5.4.4",
      "spec": "Web MIDI API",
      "text": "MIDIPortDeviceState Enum",
      "url": "https://webaudio.github.io/web-midi-api/#midiportdevicestate-enum"
    },
    "snapshot": {
      "number": "5.4.4",
      "spec": "Web MIDI API",
      "text": "MIDIPortDeviceState Enum",
      "url": "https://www.w3.org/TR/webmidi/#midiportdevicestate-enum"
    }
  },
  "#midiporttype-enum": {
    "current": {
      "number": "5.4.3",
      "spec": "Web MIDI API",
      "text": "MIDIPortType Enum",
      "url": "https://webaudio.github.io/web-midi-api/#midiporttype-enum"
    },
    "snapshot": {
      "number": "5.4.3",
      "spec": "Web MIDI API",
      "text": "MIDIPortType Enum",
      "url": "https://www.w3.org/TR/webmidi/#midiporttype-enum"
    }
  },
  "#normative-references": {
    "current": {
      "number": "A.1",
      "spec": "Web MIDI API",
      "text": "Normative references",
      "url": "https://webaudio.github.io/web-midi-api/#normative-references"
    },
    "snapshot": {
      "number": "A.1",
      "spec": "Web MIDI API",
      "text": "Normative references",
      "url": "https://www.w3.org/TR/webmidi/#normative-references"
    }
  },
  "#obtaining-access-to-midi-devices": {
    "current": {
      "number": "4",
      "spec": "Web MIDI API",
      "text": "Obtaining Access to MIDI Devices",
      "url": "https://webaudio.github.io/web-midi-api/#obtaining-access-to-midi-devices"
    },
    "snapshot": {
      "number": "4",
      "spec": "Web MIDI API",
      "text": "Obtaining Access to MIDI Devices",
      "url": "https://www.w3.org/TR/webmidi/#obtaining-access-to-midi-devices"
    }
  },
  "#permissions-integration": {
    "current": {
      "number": "4.1",
      "spec": "Web MIDI API",
      "text": "Permissions Integration",
      "url": "https://webaudio.github.io/web-midi-api/#permissions-integration"
    },
    "snapshot": {
      "number": "4.1",
      "spec": "Web MIDI API",
      "text": "Permissions Integration",
      "url": "https://www.w3.org/TR/webmidi/#permissions-integration"
    }
  },
  "#permissions-policy-integration": {
    "current": {
      "number": "4.2",
      "spec": "Web MIDI API",
      "text": "Permissions Policy Integration",
      "url": "https://webaudio.github.io/web-midi-api/#permissions-policy-integration"
    },
    "snapshot": {
      "number": "4.2",
      "spec": "Web MIDI API",
      "text": "Permissions Policy Integration",
      "url": "https://www.w3.org/TR/webmidi/#permissions-policy-integration"
    }
  },
  "#privacy-considerations": {
    "current": {
      "number": "6",
      "spec": "Web MIDI API",
      "text": "Privacy Considerations",
      "url": "https://webaudio.github.io/web-midi-api/#privacy-considerations"
    },
    "snapshot": {
      "number": "6",
      "spec": "Web MIDI API",
      "text": "Privacy Considerations",
      "url": "https://www.w3.org/TR/webmidi/#privacy-considerations"
    }
  },
  "#references": {
    "current": {
      "number": "A",
      "spec": "Web MIDI API",
      "text": "References",
      "url": "https://webaudio.github.io/web-midi-api/#references"
    },
    "snapshot": {
      "number": "A",
      "spec": "Web MIDI API",
      "text": "References",
      "url": "https://www.w3.org/TR/webmidi/#references"
    }
  },
  "#security-considerations": {
    "current": {
      "number": "7",
      "spec": "Web MIDI API",
      "text": "Security Considerations",
      "url": "https://webaudio.github.io/web-midi-api/#security-considerations"
    },
    "snapshot": {
      "number": "7",
      "spec": "Web MIDI API",
      "text": "Security Considerations",
      "url": "https://www.w3.org/TR/webmidi/#security-considerations"
    }
  },
  "#terminology": {
    "current": {
      "number": "3",
      "spec": "Web MIDI API",
      "text": "Terminology",
      "url": "https://webaudio.github.io/web-midi-api/#terminology"
    },
    "snapshot": {
      "number": "3",
      "spec": "Web MIDI API",
      "text": "Terminology",
      "url": "https://www.w3.org/TR/webmidi/#terminology"
    }
  },
  "#the-midi-api": {
    "current": {
      "number": "5",
      "spec": "Web MIDI API",
      "text": "The MIDI API",
      "url": "https://webaudio.github.io/web-midi-api/#the-midi-api"
    },
    "snapshot": {
      "number": "5",
      "spec": "Web MIDI API",
      "text": "The MIDI API",
      "url": "https://www.w3.org/TR/webmidi/#the-midi-api"
    }
  },
  "#title": {
    "current": {
      "number": "",
      "spec": "Web MIDI API",
      "text": "Web MIDI API",
      "url": "https://webaudio.github.io/web-midi-api/#title"
    },
    "snapshot": {
      "number": "",
      "spec": "Web MIDI API",
      "text": "Web MIDI API",
      "url": "https://www.w3.org/TR/webmidi/#title"
    }
  },
  "#toc": {
    "current": {
      "number": "",
      "spec": "Web MIDI API",
      "text": "Table of Contents",
      "url": "https://webaudio.github.io/web-midi-api/#toc"
    },
    "snapshot": {
      "number": "",
      "spec": "Web MIDI API",
      "text": "Table of Contents",
      "url": "https://www.w3.org/TR/webmidi/#toc"
    }
  }
}