{
  "#abstract": {
    "current": {
      "number": "",
      "spec": "Gyroscope",
      "text": "Abstract",
      "url": "https://w3c.github.io/gyroscope/#abstract"
    },
    "snapshot": {
      "number": "",
      "spec": "Gyroscope",
      "text": "Abstract",
      "url": "https://www.w3.org/TR/gyroscope/#abstract"
    }
  },
  "#abstract-operations": {
    "current": {
      "number": "8",
      "spec": "Gyroscope",
      "text": "Abstract Operations",
      "url": "https://w3c.github.io/gyroscope/#abstract-operations"
    },
    "snapshot": {
      "number": "8",
      "spec": "Gyroscope",
      "text": "Abstract Operations",
      "url": "https://www.w3.org/TR/gyroscope/#abstract-operations"
    }
  },
  "#acknowledgements": {
    "current": {
      "number": "",
      "spec": "Gyroscope",
      "text": "10. Acknowledgements",
      "url": "https://w3c.github.io/gyroscope/#acknowledgements"
    },
    "snapshot": {
      "number": "",
      "spec": "Gyroscope",
      "text": "10. Acknowledgements",
      "url": "https://www.w3.org/TR/gyroscope/#acknowledgements"
    }
  },
  "#api": {
    "current": {
      "number": "7",
      "spec": "Gyroscope",
      "text": "API",
      "url": "https://w3c.github.io/gyroscope/#api"
    },
    "snapshot": {
      "number": "7",
      "spec": "Gyroscope",
      "text": "API",
      "url": "https://www.w3.org/TR/gyroscope/#api"
    }
  },
  "#automation": {
    "current": {
      "number": "9",
      "spec": "Gyroscope",
      "text": "Automation",
      "url": "https://w3c.github.io/gyroscope/#automation"
    },
    "snapshot": {
      "number": "9",
      "spec": "Gyroscope",
      "text": "Automation",
      "url": "https://www.w3.org/TR/gyroscope/#automation"
    }
  },
  "#conformance": {
    "current": {
      "number": "",
      "spec": "Gyroscope",
      "text": "11. Conformance",
      "url": "https://w3c.github.io/gyroscope/#conformance"
    },
    "snapshot": {
      "number": "",
      "spec": "Gyroscope",
      "text": "11. Conformance",
      "url": "https://www.w3.org/TR/gyroscope/#conformance"
    }
  },
  "#construct-a-gyroscope-object": {
    "current": {
      "number": "8.1",
      "spec": "Gyroscope",
      "text": "Construct a Gyroscope object",
      "url": "https://w3c.github.io/gyroscope/#construct-a-gyroscope-object"
    },
    "snapshot": {
      "number": "8.1",
      "spec": "Gyroscope",
      "text": "Construct a Gyroscope object",
      "url": "https://www.w3.org/TR/gyroscope/#construct-a-gyroscope-object"
    }
  },
  "#examples": {
    "current": {
      "number": "3",
      "spec": "Gyroscope",
      "text": "Examples",
      "url": "https://w3c.github.io/gyroscope/#examples"
    },
    "snapshot": {
      "number": "3",
      "spec": "Gyroscope",
      "text": "Examples",
      "url": "https://www.w3.org/TR/gyroscope/#examples"
    }
  },
  "#gyroscope-interface": {
    "current": {
      "number": "7.1",
      "spec": "Gyroscope",
      "text": "The Gyroscope Interface",
      "url": "https://w3c.github.io/gyroscope/#gyroscope-interface"
    },
    "snapshot": {
      "number": "7.1",
      "spec": "Gyroscope",
      "text": "The Gyroscope Interface",
      "url": "https://www.w3.org/TR/gyroscope/#gyroscope-interface"
    }
  },
  "#gyroscope-x": {
    "current": {
      "number": "7.1.1",
      "spec": "Gyroscope",
      "text": "Gyroscope.x",
      "url": "https://w3c.github.io/gyroscope/#gyroscope-x"
    },
    "snapshot": {
      "number": "7.1.1",
      "spec": "Gyroscope",
      "text": "Gyroscope.x",
      "url": "https://www.w3.org/TR/gyroscope/#gyroscope-x"
    }
  },
  "#gyroscope-y": {
    "current": {
      "number": "7.1.2",
      "spec": "Gyroscope",
      "text": "Gyroscope.y",
      "url": "https://w3c.github.io/gyroscope/#gyroscope-y"
    },
    "snapshot": {
      "number": "7.1.2",
      "spec": "Gyroscope",
      "text": "Gyroscope.y",
      "url": "https://www.w3.org/TR/gyroscope/#gyroscope-y"
    }
  },
  "#gyroscope-z": {
    "current": {
      "number": "7.1.3",
      "spec": "Gyroscope",
      "text": "Gyroscope.z",
      "url": "https://w3c.github.io/gyroscope/#gyroscope-z"
    },
    "snapshot": {
      "number": "7.1.3",
      "spec": "Gyroscope",
      "text": "Gyroscope.z",
      "url": "https://www.w3.org/TR/gyroscope/#gyroscope-z"
    }
  },
  "#idl-index": {
    "current": {
      "number": "",
      "spec": "Gyroscope",
      "text": "IDL Index",
      "url": "https://w3c.github.io/gyroscope/#idl-index"
    },
    "snapshot": {
      "number": "",
      "spec": "Gyroscope",
      "text": "IDL Index",
      "url": "https://www.w3.org/TR/gyroscope/#idl-index"
    }
  },
  "#index": {
    "current": {
      "number": "",
      "spec": "Gyroscope",
      "text": "Index",
      "url": "https://w3c.github.io/gyroscope/#index"
    },
    "snapshot": {
      "number": "",
      "spec": "Gyroscope",
      "text": "Index",
      "url": "https://www.w3.org/TR/gyroscope/#index"
    }
  },
  "#index-defined-elsewhere": {
    "current": {
      "number": "",
      "spec": "Gyroscope",
      "text": "Terms defined by reference",
      "url": "https://w3c.github.io/gyroscope/#index-defined-elsewhere"
    },
    "snapshot": {
      "number": "",
      "spec": "Gyroscope",
      "text": "Terms defined by reference",
      "url": "https://www.w3.org/TR/gyroscope/#index-defined-elsewhere"
    }
  },
  "#index-defined-here": {
    "current": {
      "number": "",
      "spec": "Gyroscope",
      "text": "Terms defined by this specification",
      "url": "https://w3c.github.io/gyroscope/#index-defined-here"
    },
    "snapshot": {
      "number": "",
      "spec": "Gyroscope",
      "text": "Terms defined by this specification",
      "url": "https://www.w3.org/TR/gyroscope/#index-defined-here"
    }
  },
  "#informative": {
    "current": {
      "number": "",
      "spec": "Gyroscope",
      "text": "Informative References",
      "url": "https://w3c.github.io/gyroscope/#informative"
    },
    "snapshot": {
      "number": "",
      "spec": "Gyroscope",
      "text": "Informative References",
      "url": "https://www.w3.org/TR/gyroscope/#informative"
    }
  },
  "#intro": {
    "current": {
      "number": "1",
      "spec": "Gyroscope",
      "text": "Introduction",
      "url": "https://w3c.github.io/gyroscope/#intro"
    },
    "snapshot": {
      "number": "1",
      "spec": "Gyroscope",
      "text": "Introduction",
      "url": "https://www.w3.org/TR/gyroscope/#intro"
    }
  },
  "#model": {
    "current": {
      "number": "6",
      "spec": "Gyroscope",
      "text": "Model",
      "url": "https://w3c.github.io/gyroscope/#model"
    },
    "snapshot": {
      "number": "6",
      "spec": "Gyroscope",
      "text": "Model",
      "url": "https://www.w3.org/TR/gyroscope/#model"
    }
  },
  "#normative": {
    "current": {
      "number": "",
      "spec": "Gyroscope",
      "text": "Normative References",
      "url": "https://w3c.github.io/gyroscope/#normative"
    },
    "snapshot": {
      "number": "",
      "spec": "Gyroscope",
      "text": "Normative References",
      "url": "https://www.w3.org/TR/gyroscope/#normative"
    }
  },
  "#permissions-policy-integration": {
    "current": {
      "number": "5",
      "spec": "Gyroscope",
      "text": "Permissions Policy integration",
      "url": "https://w3c.github.io/gyroscope/#permissions-policy-integration"
    },
    "snapshot": {
      "number": "5",
      "spec": "Gyroscope",
      "text": "Permissions Policy integration",
      "url": "https://www.w3.org/TR/gyroscope/#permissions-policy-integration"
    }
  },
  "#reference-frame": {
    "current": {
      "number": "6.1",
      "spec": "Gyroscope",
      "text": "Reference Frame",
      "url": "https://w3c.github.io/gyroscope/#reference-frame"
    },
    "snapshot": {
      "number": "6.1",
      "spec": "Gyroscope",
      "text": "Reference Frame",
      "url": "https://www.w3.org/TR/gyroscope/#reference-frame"
    }
  },
  "#references": {
    "current": {
      "number": "",
      "spec": "Gyroscope",
      "text": "References",
      "url": "https://w3c.github.io/gyroscope/#references"
    },
    "snapshot": {
      "number": "",
      "spec": "Gyroscope",
      "text": "References",
      "url": "https://www.w3.org/TR/gyroscope/#references"
    }
  },
  "#security-and-privacy": {
    "current": {
      "number": "4",
      "spec": "Gyroscope",
      "text": "Security and Privacy Considerations",
      "url": "https://w3c.github.io/gyroscope/#security-and-privacy"
    },
    "snapshot": {
      "number": "4",
      "spec": "Gyroscope",
      "text": "Security and Privacy Considerations",
      "url": "https://www.w3.org/TR/gyroscope/#security-and-privacy"
    }
  },
  "#sotd": {
    "current": {
      "number": "",
      "spec": "Gyroscope",
      "text": "Status of this document",
      "url": "https://w3c.github.io/gyroscope/#sotd"
    },
    "snapshot": {
      "number": "",
      "spec": "Gyroscope",
      "text": "Status of this document",
      "url": "https://www.w3.org/TR/gyroscope/#sotd"
    }
  },
  "#title": {
    "current": {
      "number": "",
      "spec": "Gyroscope",
      "text": "Gyroscope",
      "url": "https://w3c.github.io/gyroscope/#title"
    },
    "snapshot": {
      "number": "",
      "spec": "Gyroscope",
      "text": "Gyroscope",
      "url": "https://www.w3.org/TR/gyroscope/#title"
    }
  },
  "#toc": {
    "current": {
      "number": "",
      "spec": "Gyroscope",
      "text": "Table of Contents",
      "url": "https://w3c.github.io/gyroscope/#toc"
    },
    "snapshot": {
      "number": "",
      "spec": "Gyroscope",
      "text": "Table of Contents",
      "url": "https://www.w3.org/TR/gyroscope/#toc"
    }
  },
  "#usecases-requirements": {
    "current": {
      "number": "2",
      "spec": "Gyroscope",
      "text": "Use Cases and Requirements",
      "url": "https://w3c.github.io/gyroscope/#usecases-requirements"
    },
    "snapshot": {
      "number": "2",
      "spec": "Gyroscope",
      "text": "Use Cases and Requirements",
      "url": "https://www.w3.org/TR/gyroscope/#usecases-requirements"
    }
  }
}